transient/__init__.py
transient/__main__.py
transient/args.py
transient/build.py
transient/checked_threading.py
transient/cli.py
transient/configuration.py
transient/editor.py
transient/image.py
transient/linux.py
transient/qemu.py
transient/scan.py
transient/ssh.py
transient/sshfs.py
transient/store.py
transient/transient.py
transient/utils.py
transient/static/__init__.py
transient/static/transient-initramfs
transient/static/transient-kernel
transient/static/transient.priv
transient/static/transient.pub
transient/static/vagrant.priv
transient/static/vagrant.pub
transient-0.25.dist-info/LICENSE
transient-0.25.dist-info/METADATA
transient-0.25.dist-info/WHEEL
transient-0.25.dist-info/entry_points.txt
transient-0.25.dist-info/top_level.txt
transient-0.25.dist-info/RECORD
