Metadata-Version: 2.1
Name: transient
Version: 0.25
Summary: A QEMU wrapper adding vagrant support and shared folders
Home-page: https://github.com/ALSchwalm/transient
Author: Adam Schwalm
License: LICENSE
Keywords: qemu
Platform: UNKNOWN
License-File: LICENSE
Requires-Dist: beautifultable (~=1.0.0)
Requires-Dist: click (~=7.1.2)
Requires-Dist: importlib-resources (~=1.5.0)
Requires-Dist: marshmallow (~=3.6.1)
Requires-Dist: lark-parser (==0.8.5)
Requires-Dist: progressbar2 (~=3.51.3)
Requires-Dist: requests (~=2.23.0)
Requires-Dist: toml (==0.10.1)
Provides-Extra: dev
Requires-Dist: black (==19.10b0) ; extra == 'dev'
Requires-Dist: mkdocs (~=1.1.2) ; extra == 'dev'
Requires-Dist: mypy (==0.800) ; extra == 'dev'
Requires-Dist: PyHamcrest (~=2.0.2) ; extra == 'dev'
Requires-Dist: typing (~=3.7.4.1) ; extra == 'dev'
Requires-Dist: behave (~=1.2.6) ; extra == 'dev'
Requires-Dist: twine (~=3.1.1) ; extra == 'dev'
Requires-Dist: wheel (==0.36.2) ; extra == 'dev'
Requires-Dist: pytest (~=6.2) ; extra == 'dev'
Requires-Dist: pytest-cov (~=2.12) ; extra == 'dev'
Requires-Dist: reformat-gherkin (~=2.0.1) ; extra == 'dev'
Requires-Dist: vulture (~=2.3) ; extra == 'dev'
